zoom_narrator/__init__.py
zoom_narrator/audio.py
zoom_narrator/captions.py
zoom_narrator/main.py
zoom_narrator/test/__init__.py
zoom_narrator/test/fixtures/Catch Me If You Can _ Frank Abagnale _ Talks at Google-vsMydMDi3rI.en.ass
zoom_narrator/test/fixtures/Catch Me If You Can _ Frank Abagnale _ Talks at Google-vsMydMDi3rI.ogg
zoom_narrator/test/fixtures/arthur the rat.mp3
zoom_narrator/test/fixtures/arthur the rat.vtt
zoom_narrator/test/fixtures/uncaptioned_audio.m4a
zoom_narrator/test/fixtures/very_simple_subs.srt
zoom_narrator/test/test_captions.py
zoom_narrator/zoom.py
zoom_narrator-1.0.1.dist-info/entry_points.txt
zoom_narrator-1.0.1.dist-info/LICENSE
zoom_narrator-1.0.1.dist-info/WHEEL
zoom_narrator-1.0.1.dist-info/METADATA
zoom_narrator-1.0.1.dist-info/RECORD
